luh3417/__init__.py
luh3417/luhfs.py
luh3417/luhphp.py
luh3417/luhsql.py
luh3417/luhssh.py
luh3417/record_set.py
luh3417/replace/__init__.py
luh3417/replace/__main__.py
luh3417/restore/__init__.py
luh3417/restore/__main__.py
luh3417/serialized_replace.py
luh3417/snapshot/__init__.py
luh3417/snapshot/__main__.py
luh3417/transfer/__init__.py
luh3417/transfer/__main__.py
luh3417/utils.py
luh3417-0.1.6.dist-info/entry_points.txt
luh3417-0.1.6.dist-info/WHEEL
luh3417-0.1.6.dist-info/METADATA
luh3417-0.1.6.dist-info/RECORD
