Metadata-Version: 2.1
Name: luh3417
Version: 0.1.6
Summary: A WordPress backup/restore/workflow tool
Home-page: https://github.com/WithIO/luh3417
License: WTFPL
Author: Rémy Sanchez
Author-email: remy.sanchez@hyperthese.net
Requires-Python: >=3.6,<4.0
Classifier: License :: Other/Proprietary License
Classifier: Programming Language :: Python :: 3
Classifier: Programming Language :: Python :: 3.6
Classifier: Programming Language :: Python :: 3.7
Classifier: Programming Language :: Python :: 3.8
Requires-Dist: apache-libcloud (>=3.0,<4.0)
Requires-Dist: coloredlogs (>=9.0)
Project-URL: Repository, https://github.com/WithIO/luh3417
